maketree/__init__.py
maketree/__main__.py
maketree/cli.py
maketree/console.py
maketree/terminal_colors.py
maketree/utils.py
maketree/core/__init__.py
maketree/core/extractor.py
maketree/core/normalizer.py
maketree/core/parser.py
maketree/core/tree_builder.py
maketree/core/tree_writer.py
maketree/core/validator.py
maketree-1.2.0.dist-info/licenses/LICENSE
tests/__init__.py
tests/test_console.py
tests/test_extractor.py
tests/test_normalizer.py
tests/test_parser.py
tests/test_terminal_colors.py
tests/test_tree_builder.py
tests/test_tree_writer.py
tests/test_utils.py
tests/test_validator.py
maketree-1.2.0.dist-info/METADATA
maketree-1.2.0.dist-info/WHEEL
maketree-1.2.0.dist-info/entry_points.txt
maketree-1.2.0.dist-info/top_level.txt
maketree-1.2.0.dist-info/RECORD
