Metadata-Version: 2.4
Name: maketree
Version: 1.2.0
Summary: Create complex project structures effortlessly.
Author-email: Anas Shakeel <srdranas456@gmail.com>
License-Expression: MIT
Project-URL: Homepage, https://github.com/anas-shakeel/maketree-cli
Project-URL: Source, https://github.com/anas-shakeel/maketree-cli
Keywords: python,cli,directory,structures,automation,file-system,scaffolding,developer-tool,productivity
Classifier: Development Status :: 5 - Production/Stable
Classifier: Intended Audience :: End Users/Desktop
Classifier: Programming Language :: Python :: 3
Classifier: Programming Language :: Python :: 3 :: Only
Classifier: Programming Language :: Python :: 3.8
Classifier: Programming Language :: Python :: 3.9
Classifier: Programming Language :: Python :: 3.10
Classifier: Programming Language :: Python :: 3.11
Classifier: Programming Language :: Python :: 3.12
Classifier: Programming Language :: Python :: 3.13
Classifier: Programming Language :: Python :: Implementation :: CPython
Classifier: Topic :: Utilities
Requires-Python: >=3.8
License-File: LICENSE
Dynamic: license-file
